[
  {
    "betAuthor": "63463e30e7377df0558ef8ea",

    "desc": "urna. Nullam lobortis quam"
  },
  {
    "betAuthor": "63463e30e7377df0558ef8eb",

    "desc": "congue turpis. In condimentum. Donec at arcu. Vestibulum ante"
  },
  {
    "betAuthor": "63463e30e7377df0558ef8ea",

    "desc": "adipiscing lacus. Ut nec urna"
  },
  {
    "betAuthor": "63463e30e7377df0558ef8eb",

    "desc": "magna sed dui. Fusce aliquam,"
  },
  {
    "betAuthor": "63463e30e7377df0558ef8eb",

    "desc": "lorem, auctor quis, tristique ac, eleifend vitae,"
  }
]
